{
  "n_states": 1277,
  "alphabet": [
    "L0",
    "L1",
    "L2",
    "L3",
    "L4"
  ],
  "start": 0,
  "graph_density": -1,
  "delta": [
    {
      "source": 0,
      "label": "L0",
      "target": 1
    },
    {
      "source": 1,
      "label": "L1",
      "target": 2
    },
    {
      "source": 2,
      "label": "L2",
      "target": 10
    },
    {
      "source": 0,
      "label": "L3",
      "target": 10
    },
    {
      "source": 10,
      "label": "L3",
      "target": 11
    },
    {
      "source": 11,
      "label": "L1",
      "target": 12
    },
    {
      "source": 12,
      "label": "L1",
      "target": 13
    },
    {
      "source": 13,
      "label": "L1",
      "target": 2
    },
    {
      "source": 10,
      "label": "L2",
      "target": 0
    },
    {
      "source": 29,
      "label": "L3",
      "target": 0
    },
    {
      "source": 2,
      "label": "L1",
      "target": 48
    },
    {
      "source": 48,
      "label": "L3",
      "target": 1
    },
    {
      "source": 1,
      "label": "L2",
      "target": 57
    },
    {
      "source": 57,
      "label": "L3",
      "target": 58
    },
    {
      "source": 58,
      "label": "L2",
      "target": 11
    },
    {
      "source": 57,
      "label": "L2",
      "target": 29
    },
    {
      "source": 48,
      "label": "L1",
      "target": 57
    },
    {
      "source": 58,
      "label": "L0",
      "target": 10
    },
    {
      "source": 12,
      "label": "L2",
      "target": 11
    },
    {
      "source": 48,
      "label": "L4",
      "target": 0
    },
    {
      "source": 48,
      "label": "L2",
      "target": 11
    },
    {
      "source": 11,
      "label": "L4",
      "target": 57
    },
    {
      "source": 158,
      "label": "L4",
      "target": 159
    },
    {
      "source": 159,
      "label": "L2",
      "target": 158
    },
    {
      "source": 12,
      "label": "L3",
      "target": 192
    },
    {
      "source": 192,
      "label": "L2",
      "target": 193
    },
    {
      "source": 193,
      "label": "L2",
      "target": 1024
    },
    {
      "source": 48,
      "label": "L0",
      "target": 203
    },
    {
      "source": 203,
      "label": "L2",
      "target": 0
    },
    {
      "source": 220,
      "label": "L1",
      "target": 12
    },
    {
      "source": 29,
      "label": "L0",
      "target": 11
    },
    {
      "source": 193,
      "label": "L3",
      "target": 203
    },
    {
      "source": 58,
      "label": "L4",
      "target": 0
    },
    {
      "source": 12,
      "label": "L4",
      "target": 0
    },
    {
      "source": 58,
      "label": "L3",
      "target": 309
    },
    {
      "source": 309,
      "label": "L1",
      "target": 310
    },
    {
      "source": 310,
      "label": "L1",
      "target": 310
    },
    {
      "source": 29,
      "label": "L2",
      "target": 57
    },
    {
      "source": 159,
      "label": "L3",
      "target": 376
    },
    {
      "source": 376,
      "label": "L1",
      "target": 58
    },
    {
      "source": 58,
      "label": "L1",
      "target": 57
    },
    {
      "source": 29,
      "label": "L4",
      "target": 10
    },
    {
      "source": 12,
      "label": "L0",
      "target": 10
    },
    {
      "source": 624,
      "label": "L1",
      "target": 908
    },
    {
      "source": 799,
      "label": "L2",
      "target": 193
    },
    {
      "source": 310,
      "label": "L2",
      "target": 821
    },
    {
      "source": 821,
      "label": "L2",
      "target": 1136
    },
    {
      "source": 220,
      "label": "L2",
      "target": 845
    },
    {
      "source": 376,
      "label": "L4",
      "target": 1
    },
    {
      "source": 29,
      "label": "L1",
      "target": 0
    },
    {
      "source": 845,
      "label": "L3",
      "target": 2
    },
    {
      "source": 908,
      "label": "L2",
      "target": 909
    },
    {
      "source": 909,
      "label": "L1",
      "target": 0
    },
    {
      "source": 13,
      "label": "L0",
      "target": 0
    },
    {
      "source": 192,
      "label": "L1",
      "target": 2
    },
    {
      "source": 158,
      "label": "L1",
      "target": 1024
    },
    {
      "source": 1024,
      "label": "L1",
      "target": 0
    },
    {
      "source": 203,
      "label": "L3",
      "target": 12
    },
    {
      "source": 1024,
      "label": "L2",
      "target": 1122
    },
    {
      "source": 1122,
      "label": "L3",
      "target": 1276
    },
    {
      "source": 1136,
      "label": "L1",
      "target": 908
    },
    {
      "source": 1024,
      "label": "L0",
      "target": 1276
    },
    {
      "source": 1276,
      "label": "L1",
      "target": 193
    },
    {
      "source": 0,
      "label": "L1",
      "target": 29
    },
    {
      "source": 0,
      "label": "L4",
      "target": 10
    },
    {
      "source": 1122,
      "label": "L2",
      "target": 1276
    },
    {
      "source": 1276,
      "label": "L4",
      "target": 1136
    },
    {
      "source": 1024,
      "label": "L4",
      "target": 159
    },
    {
      "source": 57,
      "label": "L0",
      "target": 158
    },
    {
      "source": 57,
      "label": "L1",
      "target": 220
    },
    {
      "source": 309,
      "label": "L2",
      "target": 57
    },
    {
      "source": 845,
      "label": "L2",
      "target": 0
    },
    {
      "source": 1024,
      "label": "L3",
      "target": 0
    },
    {
      "source": 2,
      "label": "L4",
      "target": 309
    },
    {
      "source": 1136,
      "label": "L0",
      "target": 0
    },
    {
      "source": 309,
      "label": "L0",
      "target": 158
    },
    {
      "source": 310,
      "label": "L0",
      "target": 58
    },
    {
      "source": 310,
      "label": "L4",
      "target": 0
    },
    {
      "source": 821,
      "label": "L4",
      "target": 0
    },
    {
      "source": 1276,
      "label": "L2",
      "target": 1276
    },
    {
      "source": 1276,
      "label": "L0",
      "target": 10
    },
    {
      "source": 908,
      "label": "L4",
      "target": 908
    },
    {
      "source": 1276,
      "label": "L3",
      "target": 11
    },
    {
      "source": 908,
      "label": "L1",
      "target": 799
    },
    {
      "source": 203,
      "label": "L4",
      "target": 220
    },
    {
      "source": 203,
      "label": "L0",
      "target": 159
    },
    {
      "source": 13,
      "label": "L2",
      "target": 2
    },
    {
      "source": 220,
      "label": "L0",
      "target": 1
    },
    {
      "source": 220,
      "label": "L3",
      "target": 1024
    },
    {
      "source": 1122,
      "label": "L1",
      "target": 1276
    },
    {
      "source": 193,
      "label": "L4",
      "target": 193
    },
    {
      "source": 193,
      "label": "L0",
      "target": 908
    },
    {
      "source": 799,
      "label": "L3",
      "target": 624
    },
    {
      "source": 799,
      "label": "L0",
      "target": 10
    },
    {
      "source": 909,
      "label": "L2",
      "target": 158
    },
    {
      "source": 1136,
      "label": "L4",
      "target": 1
    },
    {
      "source": 909,
      "label": "L3",
      "target": 12
    },
    {
      "source": 908,
      "label": "L3",
      "target": 624
    },
    {
      "source": 624,
      "label": "L3",
      "target": 2
    },
    {
      "source": 624,
      "label": "L2",
      "target": 1
    },
    {
      "source": 1122,
      "label": "L4",
      "target": 845
    }
  ]
}