{
  "n_states": 1654,
  "alphabet": [
    "L0",
    "L1",
    "L2",
    "L3",
    "L4"
  ],
  "start": 0,
  "graph_density": -1,
  "delta": [
    {
      "source": 0,
      "label": "L0",
      "target": 1
    },
    {
      "source": 1,
      "label": "L0",
      "target": 2
    },
    {
      "source": 2,
      "label": "L1",
      "target": 23
    },
    {
      "source": 2,
      "label": "L0",
      "target": 7
    },
    {
      "source": 7,
      "label": "L0",
      "target": 2
    },
    {
      "source": 1,
      "label": "L1",
      "target": 12
    },
    {
      "source": 12,
      "label": "L1",
      "target": 13
    },
    {
      "source": 13,
      "label": "L3",
      "target": 14
    },
    {
      "source": 14,
      "label": "L1",
      "target": 15
    },
    {
      "source": 15,
      "label": "L1",
      "target": 23
    },
    {
      "source": 0,
      "label": "L1",
      "target": 22
    },
    {
      "source": 22,
      "label": "L2",
      "target": 23
    },
    {
      "source": 23,
      "label": "L4",
      "target": 22
    },
    {
      "source": 13,
      "label": "L1",
      "target": 27
    },
    {
      "source": 27,
      "label": "L4",
      "target": 1
    },
    {
      "source": 22,
      "label": "L4",
      "target": 1
    },
    {
      "source": 14,
      "label": "L2",
      "target": 23
    },
    {
      "source": 14,
      "label": "L4",
      "target": 346
    },
    {
      "source": 27,
      "label": "L2",
      "target": 129
    },
    {
      "source": 129,
      "label": "L2",
      "target": 130
    },
    {
      "source": 130,
      "label": "L3",
      "target": 209
    },
    {
      "source": 23,
      "label": "L2",
      "target": 134
    },
    {
      "source": 134,
      "label": "L1",
      "target": 22
    },
    {
      "source": 7,
      "label": "L1",
      "target": 12
    },
    {
      "source": 134,
      "label": "L3",
      "target": 204
    },
    {
      "source": 204,
      "label": "L2",
      "target": 23
    },
    {
      "source": 12,
      "label": "L2",
      "target": 207
    },
    {
      "source": 207,
      "label": "L0",
      "target": 208
    },
    {
      "source": 208,
      "label": "L1",
      "target": 209
    },
    {
      "source": 209,
      "label": "L1",
      "target": 134
    },
    {
      "source": 23,
      "label": "L1",
      "target": 1
    },
    {
      "source": 129,
      "label": "L1",
      "target": 809
    },
    {
      "source": 207,
      "label": "L3",
      "target": 346
    },
    {
      "source": 346,
      "label": "L2",
      "target": 347
    },
    {
      "source": 347,
      "label": "L4",
      "target": 14
    },
    {
      "source": 209,
      "label": "L2",
      "target": 370
    },
    {
      "source": 370,
      "label": "L3",
      "target": 371
    },
    {
      "source": 371,
      "label": "L4",
      "target": 1653
    },
    {
      "source": 208,
      "label": "L0",
      "target": 2
    },
    {
      "source": 346,
      "label": "L4",
      "target": 642
    },
    {
      "source": 642,
      "label": "L0",
      "target": 1
    },
    {
      "source": 15,
      "label": "L3",
      "target": 208
    },
    {
      "source": 642,
      "label": "L3",
      "target": 1
    },
    {
      "source": 129,
      "label": "L4",
      "target": 22
    },
    {
      "source": 15,
      "label": "L0",
      "target": 1
    },
    {
      "source": 204,
      "label": "L1",
      "target": 1
    },
    {
      "source": 809,
      "label": "L0",
      "target": 810
    },
    {
      "source": 810,
      "label": "L1",
      "target": 12
    },
    {
      "source": 809,
      "label": "L1",
      "target": 12
    },
    {
      "source": 130,
      "label": "L1",
      "target": 27
    },
    {
      "source": 204,
      "label": "L4",
      "target": 948
    },
    {
      "source": 948,
      "label": "L1",
      "target": 27
    },
    {
      "source": 347,
      "label": "L2",
      "target": 13
    },
    {
      "source": 347,
      "label": "L1",
      "target": 208
    },
    {
      "source": 810,
      "label": "L0",
      "target": 1653
    },
    {
      "source": 1653,
      "label": "L1",
      "target": 209
    },
    {
      "source": 1,
      "label": "L3",
      "target": 1
    },
    {
      "source": 12,
      "label": "L4",
      "target": 22
    },
    {
      "source": 13,
      "label": "L0",
      "target": 2
    },
    {
      "source": 129,
      "label": "L3",
      "target": 22
    },
    {
      "source": 207,
      "label": "L1",
      "target": 22
    },
    {
      "source": 1653,
      "label": "L0",
      "target": 371
    },
    {
      "source": 346,
      "label": "L1",
      "target": 0
    },
    {
      "source": 27,
      "label": "L1",
      "target": 13
    },
    {
      "source": 129,
      "label": "L0",
      "target": 1
    },
    {
      "source": 948,
      "label": "L0",
      "target": 208
    },
    {
      "source": 642,
      "label": "L1",
      "target": 204
    },
    {
      "source": 370,
      "label": "L0",
      "target": 1
    },
    {
      "source": 346,
      "label": "L0",
      "target": 809
    },
    {
      "source": 0,
      "label": "L4",
      "target": 0
    },
    {
      "source": 0,
      "label": "L2",
      "target": 12
    },
    {
      "source": 371,
      "label": "L2",
      "target": 2
    },
    {
      "source": 948,
      "label": "L4",
      "target": 1
    },
    {
      "source": 370,
      "label": "L4",
      "target": 370
    },
    {
      "source": 371,
      "label": "L1",
      "target": 370
    },
    {
      "source": 1653,
      "label": "L3",
      "target": 347
    },
    {
      "source": 371,
      "label": "L0",
      "target": 130
    },
    {
      "source": 370,
      "label": "L2",
      "target": 129
    },
    {
      "source": 209,
      "label": "L3",
      "target": 0
    },
    {
      "source": 130,
      "label": "L0",
      "target": 129
    },
    {
      "source": 809,
      "label": "L2",
      "target": 13
    }
  ]
}