{
  "n_states": 624,
  "alphabet": [
    "L0",
    "L1",
    "L2",
    "L3",
    "L4"
  ],
  "start": 0,
  "graph_density": -1,
  "delta": [
    {
      "source": 0,
      "label": "L3",
      "target": 1
    },
    {
      "source": 1,
      "label": "L3",
      "target": 0
    },
    {
      "source": 1,
      "label": "L4",
      "target": 11
    },
    {
      "source": 11,
      "label": "L1",
      "target": 1
    },
    {
      "source": 0,
      "label": "L0",
      "target": 24
    },
    {
      "source": 24,
      "label": "L1",
      "target": 25
    },
    {
      "source": 25,
      "label": "L4",
      "target": 26
    },
    {
      "source": 26,
      "label": "L1",
      "target": 25
    },
    {
      "source": 25,
      "label": "L2",
      "target": 44
    },
    {
      "source": 44,
      "label": "L0",
      "target": 0
    },
    {
      "source": 26,
      "label": "L2",
      "target": 53
    },
    {
      "source": 53,
      "label": "L4",
      "target": 26
    },
    {
      "source": 24,
      "label": "L0",
      "target": 1
    },
    {
      "source": 44,
      "label": "L2",
      "target": 53
    },
    {
      "source": 53,
      "label": "L3",
      "target": 623
    },
    {
      "source": 11,
      "label": "L0",
      "target": 159
    },
    {
      "source": 159,
      "label": "L4",
      "target": 24
    },
    {
      "source": 1,
      "label": "L1",
      "target": 25
    },
    {
      "source": 159,
      "label": "L1",
      "target": 26
    },
    {
      "source": 159,
      "label": "L3",
      "target": 0
    },
    {
      "source": 44,
      "label": "L3",
      "target": 1
    },
    {
      "source": 44,
      "label": "L1",
      "target": 623
    },
    {
      "source": 623,
      "label": "L0",
      "target": 11
    },
    {
      "source": 623,
      "label": "L1",
      "target": 159
    },
    {
      "source": 623,
      "label": "L4",
      "target": 0
    }
  ]
}